{
	"success": true,
	"data": {
		"locations": [
			{ 
				"id": 1,
				"marker": {
					"position": {
						"lat": 39.908967,
						"lng": 116.397491
					},
					"map": "map",
					"title": "天安门"
				},
				"info": "天安门坐落在中国北京市中心，故宫的南端，与天安门广场隔长安街相望，是明清两代北京皇城的正门。"
			},
			{
				"id": 2,
				"marker": {
					"position": {
						"lat": 39.882435,
						"lng": 116.406595
					},
					"map": "map",
					"title": "天坛"
				},
				"info": "天坛公园位于北京市南部，东城区永定门内大街东侧，占地约270万平方米。"
			},
			{
				"id": 3,
				"marker": {
					"position": {
						"lat": 39.925099,
						"lng": 116.396715
					},
					"map": "map",
					"title": "景山公园"
				},
				"info": "景山公园位于故宫北面，为元、明、清3代的御苑，是一座环境优美的皇家园林。"
			},
			{
				"id": 4,
				"marker": {
					"position": {
						"lat": 40.000711,
						"lng": 116.275486
					},
					"map": "map",
					"title": "颐和园"
				},
				"info": "颐和园是中国现存规模最大、保存最完整的皇家园林，中国四大名园之一。"
			},
			{
				"id": 5,
				"marker": {
					"position": {
						"lat": 40.008353,
						"lng": 116.298193
					},
					"map": "map",
					"title": "圆明园"
				},
				"info": "圆明园又称圆明三园，是清代一座大型皇家宫苑，由圆明园、长春园和万春园组成，所以也叫圆明三园。"
			},
			{
				"id": 6,
				"marker": {
					"position": {
						"lat": 39.925694,
						"lng": 116.389253
					},
					"map": "map",
					"title": "北海公园"
				},
				"info": "北海公园位于北京市中心区，城内景山西侧，在故宫的西北面，与中海、南海合称三海。"
			},
			{
				"id": 7,
				"marker": {
					"position": {
						"lat": 39.953163,
						"lng": 116.416008
					},
					"map": "map",
					"title": "地坛"
				},
				"info": "地坛公园又称方泽坛，是古都北京五坛中的第二大坛。"
			}
		]
	}
}	